{
    "_type": "comparison",
    "header": "Compare for credible trust signals",
    "eyebrow": "Modern import",
    "subheadline": "Build trust with specific evidence, attribution, and compact proof points.",
    "left_title": "Compare for polished trust layer",
    "left_description": "Show quality, adoption, and outcomes with focused credibility signals.",
    "left_points": [
        "Production-ready empty and loaded states",
        "Token-aware light and dark states",
        "Accessible keyboard focus patterns"
    ],
    "left_button_text": "Open preview",
    "left_button_link": "https://ui.shadcn.com/docs/compare",
    "right_badge": "A11y checked",
    "right_title": "Compare for polished trust layer",
    "right_description": "Show quality, adoption, and outcomes with focused credibility signals.",
    "right_points": [
        "Token-aware light and dark states",
        "Accessible keyboard focus patterns",
        "Responsive cards tuned for concise content"
    ],
    "right_button_text": "Open preview",
    "right_button_link": "https://ui.shadcn.com/docs/compare"
}
