{
  "_type": "pricing",
  "header": "Plans for Every Stage",
  "eyebrow": "Plans",
  "subheadline": "From solo founders to enterprise teams, we have a plan that fits.",
  "plans": [
    {
      "title": "Solo",
      "price": "$9 /month",
      "description": "For one-person projects and early prototypes.",
      "features": [
        "1 user",
        "3 projects",
        "Basic features",
        "Community support"
      ],
      "button_text": "Start Solo",
      "button_link": "https://example.com/desiderio/pricing/solo",
      "featured": false
    },
    {
      "title": "Team",
      "price": "$25 /user/month",
      "description": "For collaborative teams shipping weekly.",
      "features": [
        "Up to 20 users",
        "Unlimited projects",
        "Advanced features",
        "Email support"
      ],
      "button_text": "Start Team",
      "button_link": "https://example.com/desiderio/pricing/team",
      "featured": true
    },
    {
      "title": "Business",
      "price": "$59 /user/month",
      "description": "For cross-functional teams with governance needs.",
      "features": [
        "Unlimited users",
        "Admin controls",
        "Analytics suite",
        "Priority support"
      ],
      "button_text": "Start Business",
      "button_link": "https://example.com/desiderio/pricing/business",
      "featured": false
    }
  ]
}
