{
    "_type": "testimonial",
    "header": "See how Northwind cut onboarding from weeks to days",
    "quote": "We cut new-hire onboarding from three weeks to two days and finally retired four spreadsheets. Managers can see exactly where every request stands, and the team adopted it without a single training session.",
    "video_url": "https://www.youtube-nocookie.com/embed/aqz-KE-bpKQ",
    "author_name": "Sofia Berg",
    "author_title": "Head of People Operations",
    "author_company": "Northwind Logistics"
}
