{
    "_type": "section",
    "header": "Built for the work you do every day",
    "shadcn_layout": "media-right",
    "subheadline": "One workspace that keeps planning, building, and reviewing in the same place.",
    "content": "<p>Stop switching between five tools to ship one project. Briefs, tasks, files, and approvals live side by side, so the next step is always obvious and nothing waits in someone's inbox.</p><ul><li>Plan work and assign owners in seconds</li><li>Review changes inline, no email threads</li><li>See real progress on one live dashboard</li></ul>",
    "media_rounded": 1,
    "button_text": "Start free trial",
    "button_link": "https://ui.shadcn.com/docs"
}
